<?xml version="1.0" encoding="utf-8" standalone="yes" ?>
<T3locallang>
	<meta type="array">
		<type>module</type>
		<description>Language labels for plugin &quot;tx_elementefenews_pi1&quot;</description>
	</meta>
	<data type="array">
		<languageKey index="default" type="array">
			<label index="form_legend">Create a new news</label>
			<label index="form_submit">Submit</label>
			<label index="form_reset">Reset</label>
			<label index="form_select">Please select</label>
			<label index="l_title">Title</label>
			<label index="l_archivedate">Archive date</label>
			<label index="l_author">Author</label>
			<label index="l_author_email">Email address</label>
			<label index="l_tx_elementefenews_author">Hide my name and email address</label>
			<label index="l_short">Subtitle</label>
            <label index="l_bodytext">Text</label>
            <label index="l_keywords">Keywords (comma separated)</label>
            <label index="l_category">Category</label>
            <label index="l_current_image">Current image</label>
			<label index="l_current_news_files">Current file</label>
            <label index="l_image">Image</label>
            <label index="l_imagecaption">Image caption</label>
            <label index="l_imagealttext">Image ALT-text</label>
            <label index="l_imagetitletext">Image TITLE-text</label>
            <label index="l_links">Links (one per line)</label>
            <label index="l_news_files">File</label>
            <label index="l_captcha">Spam protectiion</label>
			<label index="l_captcha_text">Please fill in the word shown in the image.</label>
            <label index="l_required">###SPAN_BEGIN###*###SPAN_END###</label>
            <label index="l_required_text">Fields labeled with ###SPAN_BEGIN###*###SPAN_END### are mandatory fields.</label>
            <label index="l_mail_subject">News submitted</label>
            <label index="l_mail_salutation">Dear</label>
            <label index="l_mail_intro_feed">you have submitted a new news. For your information, your data is listed following.</label>
            <label index="l_mail_intro_queue">a user has submitted a new news. Please log into the TYPO3 backend to publish this news.</label>
            <label index="l_mail_regards">Kind regards</label>
			<label index="l_error_noaccess">You don't have the rights to edit this record!</label>
			<label index="l_error_message">Input error!</label>
			<label index="l_error_field">Please fill in field ###FIELD###.</label>
			<label index="l_error_email">Field ###FIELD### must contain a valid mail-address.</label>
			<label index="l_error_archivedate">Field ###FIELD### must contain a future date.</label>
			<label index="l_error_captcha">Field ###FIELD### is not identical to the given word shown in the image.</label>
			<label index="l_error_file_mime">The file of field ###FIELD### has a not allowed file type. Allowed types are: ###MIME###.</label>
			<label index="l_error_file_ext">The file of field ###FIELD### has a not allowed file extension. Allowed extensions are: ###EXT###.</label>
			<label index="l_error_file_size">The file of field ###FIELD### filesize is bigger than allowed. The max. allowed filesize is: ###SIZE###.</label>
			
			<label index="l_no_auto_pb">No automatic pagebreaks</label>
            <label index="l_datetime">Date/Time</label>
            <label index="l_sys_language_uid">Language</label>
            <label index="l_related">Related news</label>
            <label index="l_starttime">Start</label>
            <label index="l_endtime">Stop</label>
            <label index="l_fe_group">Access</label>
            <label index="ts.confirmDelete">Are you sure you want to delete this record?</label>
		</languageKey>
		<languageKey index="de" type="array">
			<label index="form_legend">Neue Nachricht erstellen</label>
			<label index="form_submit">Absenden</label>
			<label index="form_reset">Zurücksetzen</label>
			<label index="form_select">Bitte wählen</label>
			<label index="l_title">Titel</label>
            <label index="l_archivedate">Archivdatum</label>
            <label index="l_author">Name</label>
            <label index="l_author_email">Mail-Adresse</label>
            <label index="l_tx_elementefenews_author">Meinen Namen und meine E-Mail Adresse verbergen</label>
            <label index="l_short">Untertitel</label>
            <label index="l_bodytext">Text</label>
            <label index="l_keywords">Stichworte (komma-separiert)</label>
            <label index="l_category">Kategorie</label>
            <label index="l_current_image">Aktuelles Bild</label>
			<label index="l_current_news_files">Aktuelle Datei</label>
            <label index="l_image">Bild</label>
            <label index="l_imagecaption">Bildtext</label>
            <label index="l_imagealttext">ALT-Text des Bildes</label>
            <label index="l_imagetitletext">TITLE-Text des Bildes</label>
			<label index="l_links">Links (pro Zeile einer)</label>
			<label index="l_news_files">Datei</label>
			<label index="l_captcha">Spamschutz</label>
			<label index="l_captcha_text">Bitte das Wort, welches im Bild gezeigt wird, unter "Spamschutz" eintragen.</label>
			<label index="l_required">###SPAN_BEGIN###*###SPAN_END###</label>
			<label index="l_required_text">Mit ###SPAN_BEGIN###*###SPAN_END### gekennzeichnete Felder sind Pflichtfelder.</label>
			<label index="l_mail_subject">News eingestellt</label>
			<label index="l_mail_salutation">Sehr geehrte/er</label>
            <label index="l_mail_intro_feed">Sie haben eine neue News eingestellt. Zur Information können Sie Ihre Angaben nachfolgend einsehen.</label>
            <label index="l_mail_intro_queue">ein Benutzer hat eine neue News eingestellt. Zur Information können Sie diese nachfolgend einsehen. Bitte loggen Sie sich zur Freigabe in TYPO3 ein.</label>
            <label index="l_mail_regards">Mit freundlichen Grüßen</label>
			<label index="l_error_noaccess">Sie haben nicht die erforderlichen Rechte, um diesen Datensatz bearbeiten zu dürfen.</label>
			<label index="l_error_message">Eingabefehler!</label>
			<label index="l_error_field">Bitte füllen Sie das Feld ###FIELD### aus.</label>
			<label index="l_error_email">Das Feld ###FIELD### muss eine gültige Mail-Adresse sein.</label>
			<label index="l_error_archivedate">Das Feld ###FIELD### muss ein zukünftiges Datum enthalten.</label>
			<label index="l_error_captcha">Die Datei des Feldes ###FIELD### ist nicht identisch mit dem Wort, welches im Bild gezeigt wird.</label>
			<label index="l_error_file_mime">Die Datei des Feldes ###FIELD### ist nicht vom erlaubten Typ. Erlaubte Dateitypen sind: ###MIME###.</label>
			<label index="l_error_file_ext">Die Datei des Feldes ###FIELD### hat eine nicht erlaubte Dateiendung. Erlaubte Endungen sind: ###EXT###.</label>
			<label index="l_error_file_size">Die Datei des Feldes ###FIELD### ist größer, als maximal erlaubt. Die maximale Dateigröße beträgt: ###SIZE###.</label>
			
			<label index="l_no_auto_pb">Keine Seitenumbrüche</label>
            <label index="l_datetime">Datum/Zeit</label>
            <label index="l_sys_language_uid">Sprache</label>
            <label index="l_related">In Verbindung stehende News</label>
            <label index="l_starttime">Start</label>
            <label index="l_endtime">Stop</label>
            <label index="l_fe_group">Zugriff</label>
            <label index="ts.confirmDelete">Diesen Datensatz tatsächlich löschen?</label>
		</languageKey>
		<languageKey index="fr" type="array">
			<label index="form_legend">Créer une nouvelle Actualité</label>
			<label index="form_submit">Envoyer</label>
			<label index="form_reset">Réinitialiser le formulaire</label>
			<label index="form_select">Selectionner</label>
			<label index="l_title">Titre</label>
			<label index="l_archivedate">Date d'archivage</label>
			<label index="l_author">Auteur</label>
			<label index="l_author_email">Adresse email</label>
			<label index="l_tx_elementefenews_author">Caher mon nom et mon adresse email</label>
			<label index="l_short">Sous-titre</label>
            <label index="l_bodytext">Texte</label>
            <label index="l_keywords">Mots-clé (séparés par une virgule)</label>
            <label index="l_category">Categorie</label>
            <label index="l_current_image">Image actuelle</label>
            <label index="l_image">Image</label>
            <label index="l_imagecaption">Légende de l'image</label>
            <label index="l_imagealttext">Image ALT-text</label>
            <label index="l_imagetitletext">Image TITLE-text</label>
            <label index="l_links">Liens (un par ligne)</label>
            <label index="l_news_files">Fichier</label>
            <label index="l_captcha">Protection contre le spam</label>
			<label index="l_captcha_text">Merci de recopier le mot affiché sur l'image.</label>
            <label index="l_required">###SPAN_BEGIN###*###SPAN_END###</label>
            <label index="l_required_text">Les champs marqués par ###SPAN_BEGIN###*###SPAN_END### sont obligatoires.</label>
            <label index="l_mail_subject">L'actualité est proposé à la publication</label>
            <label index="l_mail_salutation">Cher(e)</label>
            <label index="l_mail_intro_feed">Vous avez proposé une nouvelle actualité. Pour votre information, voivi les données envoyées.</label>
            <label index="l_mail_intro_queue">Un utilisateur à proposé une nouvelle actualité. Merci de vous connecter au backend de TYPO3 pour publier cette actualité.</label>
            <label index="l_mail_regards">Cordialement</label>
			<label index="l_error_noaccess">Vous n'avez pas le droit d'éditer cet enregistrement</label>
			<label index="l_error_message">Erreur de saisie !</label>
			<label index="l_error_field">Merci de renseigner le champ ###FIELD###.</label>
			<label index="l_error_email">Le champ ###FIELD###doit contenir une adresse eamil valide .</label>
			<label index="l_error_archivedate">Le champ ###FIELD### doit contenir une date posterieure à aujourd'hui.</label>
			<label index="l_error_captcha">Le champ ###FIELD### n'est pas identique au mot afficher sur l'image.</label>
			<label index="l_error_file_mime">Le type du fichier du champ ###FIELD### n'est pas autorisé . Les types de fichiers autorisés sont: ###MIME###.</label>
			<label index="l_error_file_ext">L'extension du fichier du champ ###FIELD###  n'est pas autorisée. Les extension de fichier autorisées sont: ###EXT###.</label>
			<label index="l_error_file_size">La taille du fichier du champ ###FIELD### est superieur à la taille autorisée. La taille maximum de fichier autorisée est: ###SIZE###.</label>
			
			<label index="l_no_auto_pb">No automatic pagebreaks</label>
            <label index="l_datetime">Date/Heure</label>
            <label index="l_sys_language_uid">Langue</label>
            <label index="l_related">Nouvelles en relations</label>
            <label index="l_starttime">Lancement</label>
            <label index="l_endtime">Arrêt</label>
            <label index="l_fe_group">Accès</label>
            <label index="ts.confirmDelete">Êtes-vous sûr de vouloir supprimer cet élément ?</label>
		</languageKey>
	</data>
</T3locallang>